slurm_completed_logs_utils/__init__.py
slurm_completed_logs_utils/completed_log_to_sqlite.py
slurm_completed_logs_utils/console_helper.py
slurm_completed_logs_utils/constants.py
slurm_completed_logs_utils/file_utils.py
slurm_completed_logs_utils/parser.py
slurm_completed_logs_utils/record.py
slurm_completed_logs_utils/system_caller.py
slurm_completed_logs_utils/conf/config.yaml
slurm_completed_logs_utils/sqlite/dbutil.py
slurm_completed_logs_utils/sqlite/manager.py
slurm_completed_logs_utils-0.4.0.dist-info/AUTHORS.rst
slurm_completed_logs_utils-0.4.0.dist-info/LICENSE
slurm_completed_logs_utils-0.4.0.dist-info/METADATA
slurm_completed_logs_utils-0.4.0.dist-info/WHEEL
slurm_completed_logs_utils-0.4.0.dist-info/entry_points.txt
slurm_completed_logs_utils-0.4.0.dist-info/top_level.txt
slurm_completed_logs_utils-0.4.0.dist-info/RECORD
