Metadata-Version: 2.1
Name: slurm_completed_logs_utils
Version: 0.4.0
Summary: Collection of utilities for parsing the SLURM Completed Logs file.
Home-page: https://github.com/jai-python3/slurm-completed-logs-utils
Author: Jaideep Sundaram
Author-email: jai.python3@gmail.com
Keywords: slurm_completed_logs_utils
Classifier: Development Status :: 2 - Pre-Alpha
Classifier: Intended Audience :: Developers
Classifier: Natural Language :: English
Classifier: Programming Language :: Python :: 3
Classifier: Programming Language :: Python :: 3.6
Classifier: Programming Language :: Python :: 3.7
Classifier: Programming Language :: Python :: 3.8
Requires-Python: >=3.6
License-File: LICENSE
License-File: AUTHORS.rst
Requires-Dist: Click >=7.0
Requires-Dist: Rich
Requires-Dist: pydantic
Requires-Dist: PyYAML
